LICENSE
README.md
pyproject.toml
setup.cfg
setup.py
src/cyberfusion/RabbitMQConsumerDocumentationServer/__init__.py
src/cyberfusion/RabbitMQConsumerDocumentationServer/cli.py
src/cyberfusion/RabbitMQConsumerDocumentationServer/client_models.py
src/cyberfusion/RabbitMQConsumerDocumentationServer/fastapi_server.py
src/cyberfusion/RabbitMQConsumerDocumentationServer/generator.py
src/cyberfusion/RabbitMQConsumerDocumentationServer/utilities.py
src/python3_cyberfusion_rabbitmq_consumer_documentation_server.egg-info/PKG-INFO
src/python3_cyberfusion_rabbitmq_consumer_documentation_server.egg-info/SOURCES.txt
src/python3_cyberfusion_rabbitmq_consumer_documentation_server.egg-info/dependency_links.txt
src/python3_cyberfusion_rabbitmq_consumer_documentation_server.egg-info/entry_points.txt
src/python3_cyberfusion_rabbitmq_consumer_documentation_server.egg-info/requires.txt
src/python3_cyberfusion_rabbitmq_consumer_documentation_server.egg-info/top_level.txt