Metadata-Version: 2.1
Name: python3-cyberfusion-rabbitmq-consumer-documentation-server
Version: 1.1.1
Summary: Documentation server for RabbitMQ consumer (lean RPC framework).
Home-page: https://vcs.cyberfusion.nl/core/python3-cyberfusion-rabbitmq-consumer-documentation-server
Author: William Edwards
Author-email: wedwards@cyberfusion.nl
License: MIT
Keywords: cyberfusion,rabbitmq,amqp,rpc
Platform: linux
Classifier: Programming Language :: Python :: 3
Classifier: License :: OSI Approved :: MIT License
Classifier: Operating System :: OS Independent
Requires-Python: >=3.11
License-File: LICENSE
